wavefront_package/__init__.py
wavefront_package/__main__.py
wavefront_package/circle.csv
wavefront_package/wavefront_5_pac.py
wavefront_package-1.0.9.dist-info/METADATA
wavefront_package-1.0.9.dist-info/WHEEL
wavefront_package-1.0.9.dist-info/entry_points.txt
wavefront_package-1.0.9.dist-info/top_level.txt
wavefront_package-1.0.9.dist-info/RECORD
