Metadata-Version: 2.1
Name: wavefront-package
Version: 1.0.9
Requires-Dist: numpy
Requires-Dist: matplotlib
Requires-Dist: opencv-python
